stonefish_code_shield/__init__.py
stonefish_code_shield/_cli.py
stonefish_code_shield/_console.py
stonefish_code_shield/_encrypt.py
stonefish_code_shield/_exceptions.py
stonefish_code_shield/_filetree.py
stonefish_code_shield/_helpers.py
stonefish_code_shield/_id_generators.py
stonefish_code_shield/_license_validation.py
stonefish_code_shield/_name_tree.py
stonefish_code_shield/_rename_identifiers.py
stonefish_code_shield/_stringplus.py
stonefish_code_shield/_wrap.py
stonefish_code_shield/build_meta.py
stonefish_code_shield/_merge/__init__.py
stonefish_code_shield/_merge/_api.py
stonefish_code_shield/_merge/_helpers.py
stonefish_code_shield/_merge/_main.py
stonefish_code_shield/_minify/__init__.py
stonefish_code_shield/_minify/_main.py
stonefish_code_shield-0.3.71.dist-info/METADATA
stonefish_code_shield-0.3.71.dist-info/WHEEL
stonefish_code_shield-0.3.71.dist-info/entry_points.txt
stonefish_code_shield-0.3.71.dist-info/top_level.txt
stonefish_code_shield-0.3.71.dist-info/RECORD
