Metadata-Version: 2.1
Name: stonefish-code-shield
Version: 0.3.71
Summary: Python code protection
Author-email: Nico Schlömer <nico.schloemer@gmail.com>
Project-URL: Homepage, https://github.com/stonefish-dev/code-shield
Project-URL: Issues, https://github.com/stonefish-dev/code-shield/issues
Classifier: Development Status :: 5 - Production/Stable
Classifier: License :: Other/Proprietary License
Classifier: Operating System :: OS Independent
Classifier: Programming Language :: Python
Classifier: Programming Language :: Python :: 3 :: Only
Classifier: Programming Language :: Python :: 3.9
Classifier: Programming Language :: Python :: 3.10
Classifier: Programming Language :: Python :: 3.11
Classifier: Programming Language :: Python :: 3.12
Classifier: Programming Language :: Python :: 3.13
Classifier: Topic :: Utilities
Requires-Python: >=3.9
Requires-Dist: x21 (>=0.3.71)
Requires-Dist: libcst>=0.4.6
Requires-Dist: rich>=11
Requires-Dist: rich-argparse
Requires-Dist: setuptools>=61
Requires-Dist: stonefish-license-manager>=0.4.12
Requires-Dist: tomli; python_version < "3.11"
Requires-Dist: x21>=0.4.25
